temporal/__init__.py
temporal/attention.py
temporal/data_sources.py
temporal/decoder.py
temporal/encoder.py
temporal/hf_interface.py
temporal/model.py
temporal/position_encoding.py
temporal/trainer.py
temporal/utils.py
temporal_forecasting-0.3.4.dist-info/LICENSE
temporal_forecasting-0.3.4.dist-info/METADATA
temporal_forecasting-0.3.4.dist-info/WHEEL
temporal_forecasting-0.3.4.dist-info/top_level.txt
temporal_forecasting-0.3.4.dist-info/RECORD
