Metadata-Version: 2.1
Name: temporal-forecasting
Version: 0.3.4
Summary: A transformer-based model for time series forecasting inspired by modern attention mechanisms
Author-email: Unidatum Integrated Products LLC <alex@unidatum.com>
Maintainer-email: Alex Chang <alex@unidatum.com>
License: GPL-3.0-or-later
Project-URL: Homepage, https://github.com/OptimalMatch/temporal
Project-URL: Documentation, https://github.com/OptimalMatch/temporal#readme
Project-URL: Repository, https://github.com/OptimalMatch/temporal
Project-URL: Issues, https://github.com/OptimalMatch/temporal/issues
Project-URL: Changelog, https://github.com/OptimalMatch/temporal/releases
Keywords: time-series,forecasting,transformer,deep-learning,attention-mechanism,pytorch,machine-learning,neural-network
Classifier: Development Status :: 3 - Alpha
Classifier: Intended Audience :: Developers
Classifier: Intended Audience :: Science/Research
Classifier: License :: OSI Approved :: GNU General Public License v3 or later (GPLv3+)
Classifier: Programming Language :: Python :: 3
Classifier: Programming Language :: Python :: 3.8
Classifier: Programming Language :: Python :: 3.9
Classifier: Programming Language :: Python :: 3.10
Classifier: Programming Language :: Python :: 3.11
Classifier: Programming Language :: Python :: 3.12
Classifier: Topic :: Scientific/Engineering :: Artificial Intelligence
Classifier: Topic :: Scientific/Engineering :: Information Analysis
Classifier: Operating System :: OS Independent
Requires-Python: >=3.8
License-File: LICENSE
Requires-Dist: torch>=2.0.0
Requires-Dist: numpy>=1.20.0
Requires-Dist: tqdm>=4.60.0
Requires-Dist: matplotlib>=3.3.0
Provides-Extra: all
Requires-Dist: pytest>=7.0.0; extra == "all"
Requires-Dist: black>=22.0.0; extra == "all"
Requires-Dist: flake8>=4.0.0; extra == "all"
Requires-Dist: mypy>=0.950; extra == "all"
Requires-Dist: ipython>=8.0.0; extra == "all"
Requires-Dist: sphinx>=4.0.0; extra == "all"
Requires-Dist: sphinx-rtd-theme>=1.0.0; extra == "all"
Requires-Dist: transformers>=4.30.0; extra == "all"
Requires-Dist: huggingface-hub>=0.16.0; extra == "all"
Requires-Dist: yfinance>=0.2.0; extra == "all"
Requires-Dist: pandas>=1.3.0; extra == "all"
Requires-Dist: scikit-learn>=1.0.0; extra == "all"
Requires-Dist: kagglehub>=0.2.0; extra == "all"
Provides-Extra: data
Requires-Dist: yfinance>=0.2.0; extra == "data"
Requires-Dist: pandas>=1.3.0; extra == "data"
Requires-Dist: scikit-learn>=1.0.0; extra == "data"
Requires-Dist: kagglehub>=0.2.0; extra == "data"
Provides-Extra: dev
Requires-Dist: pytest>=7.0.0; extra == "dev"
Requires-Dist: black>=22.0.0; extra == "dev"
Requires-Dist: flake8>=4.0.0; extra == "dev"
Requires-Dist: mypy>=0.950; extra == "dev"
Requires-Dist: ipython>=8.0.0; extra == "dev"
Provides-Extra: docs
Requires-Dist: sphinx>=4.0.0; extra == "docs"
Requires-Dist: sphinx-rtd-theme>=1.0.0; extra == "docs"
Provides-Extra: huggingface
Requires-Dist: transformers>=4.30.0; extra == "huggingface"
Requires-Dist: huggingface-hub>=0.16.0; extra == "huggingface"
